cBASEprogram/__init__.py
cBASEprogram/__main__.py
cBASEprogram/tests/__init__.py
cBASEprogram/tests/test_1984.py
cBASEprogram-0.0.0.dev0.dist-info/LICENSE.txt
cBASEprogram-0.0.0.dev0.dist-info/METADATA
cBASEprogram-0.0.0.dev0.dist-info/WHEEL
cBASEprogram-0.0.0.dev0.dist-info/top_level.txt
cBASEprogram-0.0.0.dev0.dist-info/RECORD
